{
  "BuildTab": {
    "BuildPath": "Chemin de création : ({0}) {1}",
    "Changelog": "Journal des modifications :",
    "JsonExtension": ".json",
    "AddPos": "Ajout POS",
    "AddPosTooltip": "Ajoute une étape DéplacerVers au chemin, AutoDuty se déplacera à la position spécifiée",
    "AddAction": "Ajout Action",
    "AddActionTooltip": "Ouvre le menu contextuel d'ajout d'action pour ajouter des étapes d'action au chemin",
    "ClearPath": "Effacer le chemin",
    "ClearPathTooltip": "Efface l'intégralité du chemin, NOTE : il n'y a pas de confirmation",
    "SavePath": "Sauvegarder le chemin",
    "SavePathTooltip": "Sauvegarde le chemin dans le fichier spécifié ou par défaut",
    "LoadPath": "Charger le chemin",
    "LoadPathTooltip": "Charge le chemin",
    "OpenFile": "Ouvrir le fichier",
    "Delete": "Supprimer",
    "CopyToClipboard": "Copier dans le presse-papiers",
    "TeleportTo": "Téléporter vers",
    "Arguments": "Arguments :",
    "Plus": "+",
    "Up": "↑",
    "Down": "↓",
    "Remove": "X",
    "Position": "Position :",
    "Note": "Note :",
    "Tag": "Balise :",
    "Conditions": "Conditions :",
    "Condition": "Condition : ",
    "AddNewCondition": "Ajouter une nouvelle condition",
    "Add": "Ajouter",
    "Modify": "Modifier",
    "SavePathError": "Vous devez ajouter au moins une action pour sauvegarder le chemin, veuillez ajouter une action et réessayer",
    "SavingPath": "Sauvegarde de {0}",
    "DataIdError": "Les {0} doivent être des uint correspondant au DataId de l'objet",
    "ErrorTitle": "Erreur",
    "NotInDungeonMessage": "Vous devez entrer dans un donjon pour créer un chemin",
    "PlusZ": "+Z",
    "MinusZ": "-Z",
    "PlusX": "+X",
    "MinusX": "-X",
    "XDiff": "Diff-X : ",
    "YDiff": "Diff-Y : ",
    "ZDiff": "Diff-Z : ",
    "Diff": "Diff : "
  }
}
